{
   "members":[
      {
         "id" : 1,
         "username":"john01",
         "firstname":"John",
         "password":"abcd",
         "roles":[
            "student"
         ]
      },
      {
         "id" : 2,
         "username":"Tim01",
         "firstname":"Tim",
         "password":"abcd",
         "roles":[
            "teacher"
         ]
      },
      {
          "id" : 3,
         "username":"Tim01",
         "firstname":"Tim",
         "password":"abcd",
         "roles":[
            "admin"
         ]
      }
   ],
   "roles":[
      {
         "name":"student"
      },
      {
         "name":"teacher"
      },
      {
         "name":"admin"
      }
   ]
}
